odoo/addons/project_task_required_project/README.rst
odoo/addons/project_task_required_project/__init__.py
odoo/addons/project_task_required_project/__manifest__.py
odoo/addons/project_task_required_project/i18n/project_task_required_project.pot
odoo/addons/project_task_required_project/models/__init__.py
odoo/addons/project_task_required_project/models/project_task.py
odoo/addons/project_task_required_project/models/res_company.py
odoo/addons/project_task_required_project/models/res_config_settings.py
odoo/addons/project_task_required_project/readme/CONFIGURE.rst
odoo/addons/project_task_required_project/readme/CONTRIBUTORS.rst
odoo/addons/project_task_required_project/readme/DESCRIPTION.rst
odoo/addons/project_task_required_project/readme/USAGE.rst
odoo/addons/project_task_required_project/static/description/icon.png
odoo/addons/project_task_required_project/static/description/index.html
odoo/addons/project_task_required_project/tests/__init__.py
odoo/addons/project_task_required_project/tests/test_project_task_required_project.py
odoo/addons/project_task_required_project/views/res_config_settings_views.xml
odoo_addon_project_task_required_project-15.0.1.0.0.2.dist-info/METADATA
odoo_addon_project_task_required_project-15.0.1.0.0.2.dist-info/WHEEL
odoo_addon_project_task_required_project-15.0.1.0.0.2.dist-info/top_level.txt
odoo_addon_project_task_required_project-15.0.1.0.0.2.dist-info/RECORD
